numismatic/__init__.py
numismatic/cli.py
numismatic/config.py
numismatic/events.py
numismatic/requesters.py
numismatic/collectors/__init__.py
numismatic/collectors/base.py
numismatic/collectors/file.py
numismatic/collectors/sql.py
numismatic/feeds/__init__.py
numismatic/feeds/base.py
numismatic/feeds/bitfinex.py
numismatic/feeds/bravenewcoin.py
numismatic/feeds/cryptocompare.py
numismatic/feeds/gdax.py
numismatic/feeds/luno.py
numismatic/feeds/poloniex.py
numismatic/libs/__init__.py
numismatic/libs/utils.py
numismatic-0.1.7.dist-info/DESCRIPTION.rst
numismatic-0.1.7.dist-info/METADATA
numismatic-0.1.7.dist-info/RECORD
numismatic-0.1.7.dist-info/WHEEL
numismatic-0.1.7.dist-info/entry_points.txt
numismatic-0.1.7.dist-info/metadata.json
numismatic-0.1.7.dist-info/top_level.txt
