Metadata-Version: 2.0
Name: numismatic
Version: 0.1.7
Summary: Coin Collector for digital assets 
Home-page: http://github.com/snth/numismatic/
Author: Tobias Brandt
Author-email: Tobias.Brandt@gmail.com
License: MIT
Keywords: bitcoin,ethereum,cryptocurrencies
Platform: UNKNOWN
Classifier: Development Status :: 3 - Alpha
Classifier: License :: OSI Approved :: MIT License
Classifier: Programming Language :: Python
Classifier: Programming Language :: Python :: 3.6
Classifier: Programming Language :: Python :: Implementation :: CPython
Requires-Python: ~=3.6
Requires-Dist: appdirs (==1.4.3)
Requires-Dist: attrs (==17.2.0)
Requires-Dist: certifi (==2017.7.27.1)
Requires-Dist: chardet (==3.0.4)
Requires-Dist: click (==6.7)
Requires-Dist: HeapDict (==1.0.0)
Requires-Dist: idna (==2.6)
Requires-Dist: python-dateutil (==2.6.1)
Requires-Dist: requests (==2.18.4)
Requires-Dist: six (==1.11.0)
Requires-Dist: streamz (==0.2.0)
Requires-Dist: toolz (==0.8.2)
Requires-Dist: tornado (==4.5.2)
Requires-Dist: urllib3 (==1.22)
Requires-Dist: websockets (==3.4)
Requires-Dist: zict (==0.1.3)
Provides-Extra: SQL
Requires-Dist: sqlalchemy; extra == 'SQL'
